partdb_labeler/__init__.py
partdb_labeler/partdb_labeler.py
partdb_labeler-0.3.1.dist-info/licenses/LICENSE
partdb_labeler-0.3.1.dist-info/METADATA
partdb_labeler-0.3.1.dist-info/WHEEL
partdb_labeler-0.3.1.dist-info/entry_points.txt
partdb_labeler-0.3.1.dist-info/top_level.txt
partdb_labeler-0.3.1.dist-info/RECORD
