Metadata-Version: 2.4
Name: partdb_labeler
Version: 0.3.1
Summary: PartDB Labeler
Home-page: https://gitlab.alfter.us/salfter/partdb-labeler
Author: Scott Alfter
Author-email: Scott Alfter <scott@alfter.us>
Requires-Python: >=3.8
License-File: LICENSE
Requires-Dist: requests
Requires-Dist: zebra
Requires-Dist: qrcode
Requires-Dist: pillow
Dynamic: license-file
